{"parentCode":"demonstrate","entity":{"id":null,"name":"汽车","parentId":20,"typeId":null,"childIds":null,"tagTypeIds":"","code":"car","customPath":true,"templatePath":"/category/list.html","path":"${category.code}/index.html","onlyUrl":false,"hasStatic":true,"url":"car/index.html","customContentPath":true,"contentPath":"${category.code}/${content.publishDate?string('yyyy/MM-dd')}/${content.id}.html","containChild":true,"pageSize":10,"allowContribute":false,"sort":0,"hidden":false},"tagTypeList":null,"attribute":{"categoryId":21,"title":"汽车 - PublicCMS","keywords":"汽车,car","description":"汽车","data":null},"modelList":[{"id":{"categoryId":21,"modelId":"picture"},"customContentPath":false,"templatePath":"/system/picture.html","contentPath":null},{"id":{"categoryId":21,"modelId":"link"},"customContentPath":false,"templatePath":"","contentPath":null},{"id":{"categoryId":21,"modelId":"article"},"customContentPath":false,"templatePath":"/system/article.html","contentPath":null}],"extendList":null,"childList":null}